Metadata-Version: 1.0
Name: knct-distributions
Version: 0.1
Summary: Gaussian and Binomial distributions
Home-page: UNKNOWN
Author: Saurabh Sharma
Author-email: srbh453@gmail.com
License: UNKNOWN
Platform: UNKNOWN
